<annotation>
	<folder>cat</folder>
	<filename>flickr_cat_000005.jpg</filename>
	<path>/home/shivani/PycharmProjects/obj-localization-animal/Tensorflow/workspace/images/collectedimages/cat/flickr_cat_000005.jpg</path>
	<source>
		<database>Unknown</database>
	</source>
	<size>
		<width>512</width>
		<height>512</height>
		<depth>3</depth>
	</size>
	<segmented>0</segmented>
	<object>
		<name>cat</name>
		<pose>Unspecified</pose>
		<truncated>0</truncated>
		<difficult>0</difficult>
		<bndbox>
			<xmin>28</xmin>
			<ymin>9</ymin>
			<xmax>460</xmax>
			<ymax>460</ymax>
		</bndbox>
	</object>
</annotation>
